bs.cp35-win_amd64.pyd
ivolat3/__init__.py
ivolat3-0.0.0.dist-info/DESCRIPTION.rst
ivolat3-0.0.0.dist-info/METADATA
ivolat3-0.0.0.dist-info/RECORD
ivolat3-0.0.0.dist-info/WHEEL
ivolat3-0.0.0.dist-info/metadata.json
ivolat3-0.0.0.dist-info/top_level.txt
