Metadata-Version: 2.0
Name: ivolat3
Version: 0.0.0
Summary: European Options Pricing Library
Home-page: https://github.com/drillan/ivolat3
Author: UNKNOWN
Author-email: UNKNOWN
License: UNKNOWN
Platform: UNKNOWN
Classifier: Programming Language :: Python :: 3
Classifier: License :: OSI Approved :: MIT License
